pgpy2/__init__.py
PGPy2-0.0.1.dist-info/LICENSE
PGPy2-0.0.1.dist-info/METADATA
PGPy2-0.0.1.dist-info/WHEEL
PGPy2-0.0.1.dist-info/top_level.txt
PGPy2-0.0.1.dist-info/RECORD
