Metadata-Version: 2.1
Name: PGPy2
Version: 0.0.1
Summary: Pretty Good Privacy for Python (forked from PGPy)
Home-page: https://github.com/dkg/PGPy2
Author: Daniel Kahn Gillmor
Author-email: dkg@fifthhorseman.net
License: BSD
Download-URL: https://github.com/dkg/PGPy2/archive/0.0.1.tar.gz
Keywords: OpenPGP,PGP,Pretty Good Privacy,GPG,GnuPG,openpgp,pgp,gnupg,gpg,encryption,signature
Platform: UNKNOWN
Classifier: Development Status :: 1 - Planning
Classifier: Operating System :: POSIX :: Linux
Classifier: Operating System :: MacOS :: MacOS X
Classifier: Operating System :: Microsoft :: Windows
Classifier: Intended Audience :: Developers
Classifier: Programming Language :: Python
Classifier: Programming Language :: Python :: 3.7
Classifier: Programming Language :: Python :: 3.6
Classifier: Programming Language :: Python :: 3.5
Classifier: Programming Language :: Python :: Implementation :: CPython
Classifier: Topic :: Security
Classifier: Topic :: Security :: Cryptography
Classifier: Topic :: Software Development :: Libraries
Classifier: Topic :: Software Development :: Libraries :: Python Modules
Classifier: License :: OSI Approved :: BSD License
